tlqb_test1/__init__.py
tlqb_test1/tlqb_test1.py
tlqb_test1-0.0.11.dist-info/LICENSE
tlqb_test1-0.0.11.dist-info/METADATA
tlqb_test1-0.0.11.dist-info/WHEEL
tlqb_test1-0.0.11.dist-info/top_level.txt
tlqb_test1-0.0.11.dist-info/RECORD
